fc_skx_bigdate.py
fc_skx1.0-1.0.dist-info/METADATA
fc_skx1.0-1.0.dist-info/WHEEL
fc_skx1.0-1.0.dist-info/top_level.txt
fc_skx1.0-1.0.dist-info/RECORD
