Metadata-Version: 2.1
Name: fc-skx1.0
Version: 1.0
Summary: skx
Home-page: UNKNOWN
Author: skx
Author-email: 1802628079@qq.com
License: UNKNOWN
Platform: UNKNOWN
